dnsviz/__init__.py
dnsviz/base32.py
dnsviz/config.py
dnsviz/crypto.py
dnsviz/format.py
dnsviz/ipaddr.py
dnsviz/query.py
dnsviz/resolver.py
dnsviz/response.py
dnsviz/transport.py
dnsviz/util.py
dnsviz/analysis/__init__.py
dnsviz/analysis/errors.py
dnsviz/analysis/offline.py
dnsviz/analysis/online.py
dnsviz/analysis/status.py
dnsviz/commands/__init__.py
dnsviz/commands/graph.py
dnsviz/commands/grok.py
dnsviz/commands/lookingglass.py
dnsviz/commands/print.py
dnsviz/commands/probe.py
dnsviz/commands/query.py
dnsviz/viz/__init__.py
dnsviz/viz/dnssec.py
dnsviz-0.11.1.data/data/share/dnsviz/css/dnsviz.css
dnsviz-0.11.1.data/data/share/dnsviz/hints/named.root
dnsviz-0.11.1.data/data/share/dnsviz/html/dnssec-template.html
dnsviz-0.11.1.data/data/share/dnsviz/icons/error.png
dnsviz-0.11.1.data/data/share/dnsviz/icons/warning.png
dnsviz-0.11.1.data/data/share/dnsviz/js/dnsviz.js
dnsviz-0.11.1.data/data/share/dnsviz/trusted-keys/root.txt
dnsviz-0.11.1.data/data/share/doc/dnsviz/README.md
dnsviz-0.11.1.data/data/share/doc/dnsviz/dnsviz-graph.html
dnsviz-0.11.1.data/data/share/doc/dnsviz/images/error.png
dnsviz-0.11.1.data/data/share/doc/dnsviz/images/logo-16x16.png
dnsviz-0.11.1.data/data/share/doc/dnsviz/images/logo-220x100.png
dnsviz-0.11.1.data/data/share/doc/dnsviz/images/logo-60x60.png
dnsviz-0.11.1.data/data/share/doc/dnsviz/images/warning.png
dnsviz-0.11.1.data/data/share/man/man1/dnsviz-graph.1
dnsviz-0.11.1.data/data/share/man/man1/dnsviz-grok.1
dnsviz-0.11.1.data/data/share/man/man1/dnsviz-print.1
dnsviz-0.11.1.data/data/share/man/man1/dnsviz-probe.1
dnsviz-0.11.1.data/data/share/man/man1/dnsviz-query.1
dnsviz-0.11.1.data/data/share/man/man1/dnsviz.1
dnsviz-0.11.1.data/scripts/dnsviz
dnsviz-0.11.1.dist-info/licenses/COPYRIGHT
dnsviz-0.11.1.dist-info/licenses/LICENSE
dnsviz-0.11.1.dist-info/METADATA
dnsviz-0.11.1.dist-info/WHEEL
dnsviz-0.11.1.dist-info/top_level.txt
dnsviz-0.11.1.dist-info/RECORD
