Metadata-Version: 2.4
Name: dnsviz
Version: 0.11.1
Summary: DNS analysis and visualization tool suite
Home-page: https://github.com/dnsviz/dnsviz/
Author: Casey Deccio
Author-email: casey@deccio.net
License: LICENSE
Classifier: Development Status :: 5 - Production/Stable
Classifier: Environment :: Console
Classifier: Environment :: Web Environment
Classifier: Intended Audience :: Developers
Classifier: Intended Audience :: System Administrators
Classifier: License :: OSI Approved :: GNU General Public License v2 or later (GPLv2+)
Classifier: Natural Language :: English
Classifier: Operating System :: MacOS :: MacOS X
Classifier: Operating System :: POSIX
Classifier: Programming Language :: Python :: 2.7
Classifier: Programming Language :: Python :: 3.5
Classifier: Programming Language :: Python :: 3.6
Classifier: Programming Language :: Python :: 3.7
Classifier: Programming Language :: Python :: 3.8
Classifier: Programming Language :: Python :: 3.9
Classifier: Programming Language :: Python :: 3.10
Classifier: Programming Language :: Python :: 3.11
Classifier: Programming Language :: Python :: 3.12
Classifier: Topic :: Internet :: Name Service (DNS)
Classifier: Topic :: Scientific/Engineering :: Visualization
Classifier: Topic :: System :: Networking :: Monitoring
Requires: pygraphviz (>=1.3)
Requires: cryptography (>=36.0.0)
Requires: dnspython (>=1.13)
License-File: LICENSE
License-File: COPYRIGHT
Dynamic: author
Dynamic: author-email
Dynamic: classifier
Dynamic: description
Dynamic: home-page
Dynamic: license
Dynamic: license-file
Dynamic: requires
Dynamic: summary
